claude_linear-0.1.6.dist-info/licenses/LICENSE
cli/__init__.py
cli/init.py
cli/labels.py
cli/main.py
cli/setup.py
cli/utils.py
cli/validate.py
shared/__init__.py
shared/constants.py
claude_linear-0.1.6.dist-info/METADATA
claude_linear-0.1.6.dist-info/WHEEL
claude_linear-0.1.6.dist-info/entry_points.txt
claude_linear-0.1.6.dist-info/top_level.txt
claude_linear-0.1.6.dist-info/RECORD
