Metadata-Version: 2.4
Name: claude-linear
Version: 0.1.6
Summary: Automate software development with Claude Code, Linear, and GitHub Actions
Author: Anthropic
License: MIT
Project-URL: Homepage, https://github.com/anthropics/claude-linear-automation
Project-URL: Documentation, https://github.com/anthropics/claude-linear-automation#readme
Project-URL: Repository, https://github.com/anthropics/claude-linear-automation
Project-URL: Issues, https://github.com/anthropics/claude-linear-automation/issues
Keywords: claude,linear,github-actions,automation,ai,developer-tools
Classifier: Development Status :: 4 - Beta
Classifier: Environment :: Console
Classifier: Intended Audience :: Developers
Classifier: License :: OSI Approved :: MIT License
Classifier: Operating System :: OS Independent
Classifier: Programming Language :: Python :: 3
Classifier: Programming Language :: Python :: 3.11
Classifier: Programming Language :: Python :: 3.12
Classifier: Topic :: Software Development :: Build Tools
Classifier: Topic :: Software Development :: Quality Assurance
Requires-Python: >=3.11
License-File: LICENSE
Requires-Dist: click>=8.0.0
Requires-Dist: httpx>=0.28.0
Requires-Dist: pydantic>=2.10.0
Requires-Dist: pydantic-settings>=2.7.0
Requires-Dist: python-dotenv>=1.0.0
Provides-Extra: server
Requires-Dist: fastapi>=0.115.0; extra == "server"
Requires-Dist: uvicorn>=0.30.0; extra == "server"
Requires-Dist: slowapi>=0.1.9; extra == "server"
Provides-Extra: dev
Requires-Dist: pre-commit>=3.6.0; extra == "dev"
Requires-Dist: ruff>=0.8.0; extra == "dev"
Requires-Dist: mypy>=1.13.0; extra == "dev"
Requires-Dist: pytest>=8.0.0; extra == "dev"
Requires-Dist: pytest-asyncio>=0.24.0; extra == "dev"
Requires-Dist: bandit>=1.7.0; extra == "dev"
Provides-Extra: all
Requires-Dist: claude-linear[dev,server]; extra == "all"
Dynamic: license-file
